_pybcp.cpython-312-x86_64-linux-gnu.so
pybcp.py
pybcp.libs/libcrypto-101e1754.so.3.0.7
pybcp.libs/libssl-b01c5100.so.3.0.7
pybcp.libs/libsybdb-2c501919.so.5.1.0
pybcp-0.1.3.dist-info/METADATA
pybcp-0.1.3.dist-info/WHEEL
pybcp-0.1.3.dist-info/RECORD
