Metadata-Version: 2.1
Name: pybcp
Version: 0.1.3
Summary: Tool for importing data to MS SQL Server.
Author-Email: John Helly <j.c.helly@durham.ac.uk>
Classifier: Programming Language :: Python :: 3
Classifier: License :: OSI Approved :: GNU General Public License v3 (GPLv3)
Classifier: Operating System :: OS Independent
Requires-Python: >=3.10
Requires-Dist: numpy
